client/__init__.py
client/launcher_for_ubuntu.py
client/launcher_for_windows.py
client/start_client.py
client/client/__init__.py
client/client/client_db.py
client/client/login_dialog.py
client/client/login_dialog_ui.py
client/client/main_window.py
client/client/main_window_ui.py
client/client/transport.py
client/common/__init__.py
client/common/errors.py
client/common/globals.py
client/common/utils.py
client/log/__init__.py
client/log/client_log_config.py
client/log/decorator.py
pyqt_hyperchat_client-0.1.81.data/scripts/client_run
pyqt_hyperchat_client-0.1.81.dist-info/METADATA
pyqt_hyperchat_client-0.1.81.dist-info/WHEEL
pyqt_hyperchat_client-0.1.81.dist-info/top_level.txt
pyqt_hyperchat_client-0.1.81.dist-info/RECORD
